qrs_wrapper/__init__.py
qrs_wrapper/qrs_wrapper.py
qrs_wrapper/wrapper_map.py
qrs_wrapper-0.1.1.dist-info/WHEEL
qrs_wrapper-0.1.1.dist-info/METADATA
qrs_wrapper-0.1.1.dist-info/RECORD
