Metadata-Version: 2.1
Name: qrs-wrapper
Version: 0.1.1
Summary: "Produce R peaks estimation on top of libraries specialized in ecg data processing"
Author: GiovanniLB
Author-email: globianco29@gmail.com
Requires-Python: >=3.8,<4.0
Classifier: Programming Language :: Python :: 3
Classifier: Programming Language :: Python :: 3.8
Classifier: Programming Language :: Python :: 3.9
Classifier: Programming Language :: Python :: 3.10
Classifier: Programming Language :: Python :: 3.11
Requires-Dist: biosppy (>=1.0.0,<2.0.0)
Requires-Dist: neurokit2 (>=0.2.1,<0.3.0)
Requires-Dist: numpy (>=1.23.4,<2.0.0)
Requires-Dist: py-ecg-detectors (>=1.3.2,<2.0.0)
